Metadata-Version: 1.0
Name: pyIGRF
Version: 0.3.0
Summary: IGRF-12 Model by Python
Home-page: https://github.com/zzyztyy/pyIGRF
Author: zzyztyy
Author-email: 2375672032@qq.com
License: MIT
Platform: UNKNOWN
